pytest_dogu_report/__init__.py
pytest_dogu_report/protocols.py
pytest_dogu_report/step_reporter.py
pytest_dogu_report-1.0.1.dist-info/METADATA
pytest_dogu_report-1.0.1.dist-info/WHEEL
pytest_dogu_report-1.0.1.dist-info/RECORD
