Metadata-Version: 2.1
Name: pytest-dogu-report
Version: 1.0.1
Summary: pytest plugin for dogu report
Author: henry
Requires-Python: >=3.9,<4.0
Classifier: Programming Language :: Python :: 3
Classifier: Programming Language :: Python :: 3.9
Classifier: Programming Language :: Python :: 3.10
Classifier: Programming Language :: Python :: 3.11
Requires-Dist: dacite (>=1.8.1,<2.0.0)
Requires-Dist: requests (>=2.31.0,<3.0.0)
